PySimpleEven/__init__.py
PySimpleEven/is_even.py
pysimpleeven-0.1.0.dist-info/licenses/LICENSE
pysimpleeven-0.1.0.dist-info/METADATA
pysimpleeven-0.1.0.dist-info/WHEEL
pysimpleeven-0.1.0.dist-info/top_level.txt
pysimpleeven-0.1.0.dist-info/RECORD
