Metadata-Version: 2.4
Name: PySimpleEven
Version: 0.1.0
Summary: Ver se um número é par ou impar.
Home-page: https://github.com/oDaniel728/py-simple-even
Author: Daniel Menezes
Author-email: danielmenezes0822@gmail.com
Classifier: Programming Language :: Python :: 3
Classifier: License :: OSI Approved :: MIT License
Classifier: Operating System :: OS Independent
Requires-Python: >=3.8
License-File: LICENSE
Dynamic: license-file
